csp_slack/__init__.py
csp_slack/tests/test_all.py
csp_slack-0.1.0.dist-info/METADATA
csp_slack-0.1.0.dist-info/WHEEL
csp_slack-0.1.0.dist-info/licenses/LICENSE
csp_slack-0.1.0.dist-info/RECORD
